django_applepodcast-0.3.7.dist-info/DESCRIPTION.rst
django_applepodcast-0.3.7.dist-info/METADATA
django_applepodcast-0.3.7.dist-info/RECORD
django_applepodcast-0.3.7.dist-info/WHEEL
django_applepodcast-0.3.7.dist-info/metadata.json
django_applepodcast-0.3.7.dist-info/top_level.txt
podcast/__init__.py
podcast/admin.py
podcast/apps.py
podcast/feeds.py
podcast/managers.py
podcast/models.py
podcast/settings.py
podcast/urls.py
podcast/utils.py
podcast/views.py
podcast/fixtures/podcast_category.json
podcast/migrations/0001_initial.py
podcast/migrations/0002_remove_episode_order.py
podcast/migrations/0003_remove_show_ttl.py
podcast/migrations/0004_auto_20170917_0503.py
podcast/migrations/0005_episode_guid.py
podcast/migrations/0006_auto_20170920_1833.py
podcast/migrations/0007_auto_20170920_2212.py
podcast/migrations/0008_auto_20170920_2212.py
podcast/migrations/0009_auto_20170923_0129.py
podcast/migrations/0010_auto_20170923_0131.py
podcast/migrations/0011_episode_itunes_title.py
podcast/migrations/0012_episode_type.py
podcast/migrations/0013_episode_number.py
podcast/migrations/0014_episode_season.py
podcast/migrations/0015_show_type.py
podcast/migrations/0016_auto_20170923_2000.py
podcast/migrations/0017_auto_20170923_2133.py
podcast/migrations/0018_auto_20170924_0609.py
podcast/migrations/0019_auto_20170924_1839.py
podcast/migrations/0020_auto_20171026_2121.py
podcast/migrations/0021_auto_20171028_1742.py
podcast/migrations/0022_remove_category_json.py
podcast/migrations/0023_auto_20171121_2139.py
podcast/migrations/0024_show_ttl.py
podcast/migrations/0025_auto_20171211_0342.py
podcast/migrations/0026_auto_20171211_0342.py
podcast/migrations/0027_auto_20171211_0424.py
podcast/migrations/0028_auto_20171211_0424.py
podcast/migrations/0029_auto_20171211_0424.py
podcast/migrations/__init__.py
podcast/static/podcast/.DS_Store
podcast/static/podcast/img/.DS_Store
podcast/static/podcast/img/badge.svg
podcast/static/podcast/img/icon-black.svg
podcast/static/podcast/img/icon-white.svg
podcast/static/podcast/img/icon.svg
podcast/static/podcast/img/no_artwork.png
podcast/templates/.DS_Store
podcast/templates/base.html
podcast/templates/podcast/episode_detail.html
podcast/templates/podcast/pagination.html
